tf_extensions/__init__.py
tf_extensions/auxiliary/__init__.py
tf_extensions/auxiliary/base_config.py
tf_extensions/auxiliary/custom_types.py
tf_extensions/auxiliary/tf_utils.py
tf_extensions/layers/__init__.py
tf_extensions/layers/aspp_layer.py
tf_extensions/layers/attention_gating_block.py
tf_extensions/layers/base_layer.py
tf_extensions/layers/conv_configs.py
tf_extensions/layers/convolutional_block.py
tf_extensions/layers/gating.py
tf_extensions/layers/max_pooling.py
tf_extensions/layers/max_unpooling.py
tf_extensions/layers/skipped_connections.py
tf_extensions/layers/u_net_output.py
tf_extensions/losses/__init__.py
tf_extensions/losses/base_loss.py
tf_extensions/losses/combined_loss.py
tf_extensions/losses/dists.py
tf_extensions/losses/dssim.py
tf_extensions/losses/fft.py
tf_extensions/losses/ms_dssim.py
tf_extensions/losses/multiscale_loss.py
tf_extensions/losses/soft_dice.py
tf_extensions/losses/ssim_calculator.py
tf_extensions/losses/supported_losses.py
tf_extensions/losses/vgg.py
tf_extensions/losses/vgg_base.py
tf_extensions/models/__init__.py
tf_extensions/models/aspp_net.py
tf_extensions/models/base_cnn.py
tf_extensions/models/base_net.py
tf_extensions/models/seg_net.py
tf_extensions/models/u_net.py
tf_extensions-0.1.0.dist-info/METADATA
tf_extensions-0.1.0.dist-info/WHEEL
tf_extensions-0.1.0.dist-info/licenses/LICENSE
tf_extensions-0.1.0.dist-info/RECORD
