Metadata-Version: 2.4
Name: tf-extensions
Version: 0.1.0
Author: albertfarhutdinov@gmail.com
License: MIT
License-File: LICENSE
Requires-Python: <3.12,>=3.9
Requires-Dist: ipython<9.1
Requires-Dist: keras<2.15
Requires-Dist: numpy<1.24
Requires-Dist: pytest<8.4
Requires-Dist: pyyaml<6.1
Requires-Dist: tensorflow-intel<2.15; sys_platform == 'win32'
Requires-Dist: tensorflow-io-gcs-filesystem<0.32.0; sys_platform == 'win32'
Requires-Dist: tensorflow<2.15
